{
    "ID": "1001240",
    "Typing": null,
    "Class": null,
    "Name": "Dr. Gero",
    "Rarity": "r",
    "Max Level": "40",
    "Max HP": "5312",
    "Max ATK": "3465",
    "Max DEF": "3555",
    "Categories": [
        "Androids",
        "Androids/Cell Saga",
        "Terrifying Conquerors",
        "Target: Goku",
        "Revenge",
        "Battle of Wits",
        "Power Absorption"
    ],
    "Links": [
        "Android Assault",
        "RR Army",
        "Flee",
        "Thirst for Conquest",
        "Scientist",
        "Energy Absorption"
    ],
    "Passive": {},
    "Hidden Potential": {},
    "Active Skill": {},
    "Super Attack": null,
    "Standby Skill": {}
}