{
    "ID": "1021871",
    "Typing": "TEQ",
    "Class": "Super",
    "Name": "Krillin",
    "Rarity": "ur",
    "Min Level": 1,
    "Max Level": 120,
    "Categories": [
        "Saviors",
        "Movie Heroes",
        "Earthlings",
        "Kamehameha",
        "Battle of Wits",
        "Turtle School",
        "Bond of Friendship",
        "Earth-Bred Fighters"
    ],
    "Links": [
        "Turtle School",
        "Experienced Fighters",
        "Courage",
        "High Compatibility",
        "Solid Support",
        "Kamehameha",
        "Fierce Battle"
    ],
    "Resource ID": "1021870",
    "Passive": {
        "2393": {
            "ID": "2393",
            "Timing": "Start of turn",
            "ATK": 120,
            "DEF": 120,
            "Target": {
                "Target": "Self"
            },
            "Buff": {
                "Type": "Percentage",
                "+ or -": "+"
            },
            "Length": "1"
        },
        "1002393": {
            "ID": "1002393",
            "Timing": "Start of turn",
            "Ki": 2,
            "Target": {
                "Target": "Allies",
                "Class": "Super"
            },
            "Buff": {
                "Type": "Raw stats",
                "+ or -": "+"
            },
            "Length": "1"
        },
        "2002393": {
            "ID": "2002393",
            "Timing": "Start of turn",
            "ATK": 30,
            "DEF": 30,
            "Target": {
                "Target": "Allies",
                "Class": "Super"
            },
            "Buff": {
                "Type": "Percentage",
                "+ or -": "+"
            },
            "Length": "1"
        },
        "3002393": {
            "ID": "3002393",
            "Timing": "Start of turn",
            "ATK": 120,
            "Target": {
                "Target": "Self"
            },
            "Buff": {
                "Type": "Percentage",
                "+ or -": "+"
            },
            "Length": "1",
            "Condition": {
                "Logic": "623 || 624",
                "Causalities": {
                    "623": {
                        "Button": {
                            "Name": "Is there is an ally attacking in the same turn whose name includes Trunks (Kid)?"
                        }
                    },
                    "624": {
                        "Button": {
                            "Name": "Is there is an ally attacking in the same turn whose name includes Goten (Kid)?"
                        }
                    }
                }
            }
        },
        "4002393": {
            "ID": "4002393",
            "Timing": "Start of turn",
            "DR": 30,
            "Target": {
                "Target": "Self"
            },
            "Buff": {
                "Type": "Percentage",
                "+ or -": "+"
            },
            "Length": "1",
            "Condition": {
                "Logic": "623 || 624",
                "Causalities": {
                    "623": {
                        "Button": {
                            "Name": "Is there is an ally attacking in the same turn whose name includes Trunks (Kid)?"
                        }
                    },
                    "624": {
                        "Button": {
                            "Name": "Is there is an ally attacking in the same turn whose name includes Goten (Kid)?"
                        }
                    }
                }
            }
        },
        "5002393": {
            "ID": "5002393",
            "Timing": "Start of turn",
            "Ki": 2,
            "Target": {
                "Target": "Allies",
                "Class": "Super"
            },
            "Buff": {
                "Type": "Raw stats",
                "+ or -": "+"
            },
            "Length": "1",
            "Condition": {
                "Logic": "623 || 624",
                "Causalities": {
                    "623": {
                        "Button": {
                            "Name": "Is there is an ally attacking in the same turn whose name includes Trunks (Kid)?"
                        }
                    },
                    "624": {
                        "Button": {
                            "Name": "Is there is an ally attacking in the same turn whose name includes Goten (Kid)?"
                        }
                    }
                }
            }
        },
        "6002393": {
            "ID": "6002393",
            "Timing": "Start of turn",
            "ATK": 30,
            "DEF": 30,
            "Target": {
                "Target": "Allies",
                "Class": "Super"
            },
            "Buff": {
                "Type": "Percentage",
                "+ or -": "+"
            },
            "Length": "1",
            "Condition": {
                "Logic": "623 || 624",
                "Causalities": {
                    "623": {
                        "Button": {
                            "Name": "Is there is an ally attacking in the same turn whose name includes Trunks (Kid)?"
                        }
                    },
                    "624": {
                        "Button": {
                            "Name": "Is there is an ally attacking in the same turn whose name includes Goten (Kid)?"
                        }
                    }
                }
            }
        },
        "7002393": {
            "ID": "7002393",
            "Timing": "Start of turn",
            "DR": 10,
            "Target": {
                "Target": "Self"
            },
            "Buff": {
                "Type": "Percentage",
                "+ or -": "+"
            },
            "Length": "1",
            "Condition": {
                "Logic": "487",
                "Causalities": {
                    "487": {
                        "Button": {
                            "Name": "Are there 1 or more Movie Bosses category enemies "
                        },
                        "Slider": {
                            "Name": "How many Movie Bosses category enemies ",
                            "Logic": ">=1",
                            "Max": 7,
                            "Min": 0
                        }
                    }
                }
            }
        },
        "8002393": {
            "ID": "8002393",
            "Timing": "Start of turn",
            "Crit Chance": 10,
            "Target": {
                "Target": "Allies",
                "Class": "Super"
            },
            "Buff": {
                "Type": "Percentage",
                "+ or -": "+"
            },
            "Length": "1",
            "Condition": {
                "Logic": "487",
                "Causalities": {
                    "487": {
                        "Button": {
                            "Name": "Are there 1 or more Movie Bosses category enemies "
                        },
                        "Slider": {
                            "Name": "How many Movie Bosses category enemies ",
                            "Logic": ">=1",
                            "Max": 7,
                            "Min": 0
                        }
                    }
                }
            }
        }
    },
    "Max Attacks": 2,
    "Max Super Attacks": 2,
    "Stats at levels": {
        "1": {
            "HP": 2654,
            "ATK": 2802,
            "DEF": 1464
        },
        "2": {
            "HP": 2703,
            "ATK": 2855,
            "DEF": 1490
        },
        "3": {
            "HP": 2755,
            "ATK": 2913,
            "DEF": 1519
        },
        "4": {
            "HP": 2804,
            "ATK": 2966,
            "DEF": 1546
        },
        "5": {
            "HP": 2856,
            "ATK": 3024,
            "DEF": 1574
        },
        "6": {
            "HP": 2906,
            "ATK": 3078,
            "DEF": 1601
        },
        "7": {
            "HP": 2955,
            "ATK": 3131,
            "DEF": 1628
        },
        "8": {
            "HP": 3007,
            "ATK": 3189,
            "DEF": 1656
        },
        "9": {
            "HP": 3056,
            "ATK": 3243,
            "DEF": 1683
        },
        "10": {
            "HP": 3109,
            "ATK": 3300,
            "DEF": 1711
        },
        "11": {
            "HP": 3158,
            "ATK": 3354,
            "DEF": 1738
        },
        "12": {
            "HP": 3207,
            "ATK": 3408,
            "DEF": 1765
        },
        "13": {
            "HP": 3259,
            "ATK": 3465,
            "DEF": 1793
        },
        "14": {
            "HP": 3309,
            "ATK": 3519,
            "DEF": 1820
        },
        "15": {
            "HP": 3361,
            "ATK": 3576,
            "DEF": 1849
        },
        "16": {
            "HP": 3410,
            "ATK": 3630,
            "DEF": 1875
        },
        "17": {
            "HP": 3459,
            "ATK": 3684,
            "DEF": 1902
        },
        "18": {
            "HP": 3512,
            "ATK": 3741,
            "DEF": 1931
        },
        "19": {
            "HP": 3561,
            "ATK": 3795,
            "DEF": 1958
        },
        "20": {
            "HP": 3613,
            "ATK": 3852,
            "DEF": 1986
        },
        "21": {
            "HP": 3662,
            "ATK": 3906,
            "DEF": 2013
        },
        "22": {
            "HP": 3712,
            "ATK": 3960,
            "DEF": 2040
        },
        "23": {
            "HP": 3764,
            "ATK": 4017,
            "DEF": 2068
        },
        "24": {
            "HP": 3813,
            "ATK": 4071,
            "DEF": 2095
        },
        "25": {
            "HP": 3865,
            "ATK": 4128,
            "DEF": 2123
        },
        "26": {
            "HP": 3915,
            "ATK": 4182,
            "DEF": 2150
        },
        "27": {
            "HP": 3964,
            "ATK": 4236,
            "DEF": 2177
        },
        "28": {
            "HP": 4016,
            "ATK": 4293,
            "DEF": 2205
        },
        "29": {
            "HP": 4065,
            "ATK": 4347,
            "DEF": 2232
        },
        "30": {
            "HP": 4118,
            "ATK": 4404,
            "DEF": 2261
        },
        "31": {
            "HP": 4167,
            "ATK": 4458,
            "DEF": 2287
        },
        "32": {
            "HP": 4219,
            "ATK": 4515,
            "DEF": 2316
        },
        "33": {
            "HP": 4268,
            "ATK": 4569,
            "DEF": 2343
        },
        "34": {
            "HP": 4318,
            "ATK": 4623,
            "DEF": 2370
        },
        "35": {
            "HP": 4370,
            "ATK": 4680,
            "DEF": 2398
        },
        "36": {
            "HP": 4419,
            "ATK": 4734,
            "DEF": 2425
        },
        "37": {
            "HP": 4471,
            "ATK": 4791,
            "DEF": 2453
        },
        "38": {
            "HP": 4521,
            "ATK": 4845,
            "DEF": 2480
        },
        "39": {
            "HP": 4570,
            "ATK": 4899,
            "DEF": 2507
        },
        "40": {
            "HP": 4622,
            "ATK": 4956,
            "DEF": 2535
        },
        "41": {
            "HP": 4671,
            "ATK": 5010,
            "DEF": 2562
        },
        "42": {
            "HP": 4723,
            "ATK": 5067,
            "DEF": 2591
        },
        "43": {
            "HP": 4773,
            "ATK": 5121,
            "DEF": 2617
        },
        "44": {
            "HP": 4822,
            "ATK": 5175,
            "DEF": 2644
        },
        "45": {
            "HP": 4874,
            "ATK": 5232,
            "DEF": 2673
        },
        "46": {
            "HP": 4923,
            "ATK": 5286,
            "DEF": 2699
        },
        "47": {
            "HP": 4976,
            "ATK": 5343,
            "DEF": 2728
        },
        "48": {
            "HP": 5025,
            "ATK": 5397,
            "DEF": 2755
        },
        "49": {
            "HP": 5074,
            "ATK": 5451,
            "DEF": 2781
        },
        "50": {
            "HP": 5126,
            "ATK": 5508,
            "DEF": 2810
        },
        "51": {
            "HP": 5176,
            "ATK": 5562,
            "DEF": 2837
        },
        "52": {
            "HP": 5228,
            "ATK": 5619,
            "DEF": 2865
        },
        "53": {
            "HP": 5277,
            "ATK": 5673,
            "DEF": 2892
        },
        "54": {
            "HP": 5326,
            "ATK": 5727,
            "DEF": 2919
        },
        "55": {
            "HP": 5379,
            "ATK": 5784,
            "DEF": 2947
        },
        "56": {
            "HP": 5428,
            "ATK": 5838,
            "DEF": 2974
        },
        "57": {
            "HP": 5480,
            "ATK": 5896,
            "DEF": 3003
        },
        "58": {
            "HP": 5529,
            "ATK": 5949,
            "DEF": 3029
        },
        "59": {
            "HP": 5579,
            "ATK": 6003,
            "DEF": 3056
        },
        "60": {
            "HP": 5631,
            "ATK": 6061,
            "DEF": 3085
        },
        "61": {
            "HP": 5680,
            "ATK": 6114,
            "DEF": 3111
        },
        "62": {
            "HP": 5732,
            "ATK": 6172,
            "DEF": 3140
        },
        "63": {
            "HP": 5782,
            "ATK": 6226,
            "DEF": 3167
        },
        "64": {
            "HP": 5831,
            "ATK": 6279,
            "DEF": 3193
        },
        "65": {
            "HP": 5883,
            "ATK": 6337,
            "DEF": 3222
        },
        "66": {
            "HP": 5932,
            "ATK": 6391,
            "DEF": 3249
        },
        "67": {
            "HP": 5985,
            "ATK": 6448,
            "DEF": 3277
        },
        "68": {
            "HP": 6034,
            "ATK": 6502,
            "DEF": 3304
        },
        "69": {
            "HP": 6083,
            "ATK": 6556,
            "DEF": 3331
        },
        "70": {
            "HP": 6135,
            "ATK": 6613,
            "DEF": 3359
        },
        "71": {
            "HP": 6185,
            "ATK": 6667,
            "DEF": 3386
        },
        "72": {
            "HP": 6237,
            "ATK": 6724,
            "DEF": 3415
        },
        "73": {
            "HP": 6286,
            "ATK": 6778,
            "DEF": 3441
        },
        "74": {
            "HP": 6335,
            "ATK": 6832,
            "DEF": 3468
        },
        "75": {
            "HP": 6388,
            "ATK": 6889,
            "DEF": 3497
        },
        "76": {
            "HP": 6437,
            "ATK": 6943,
            "DEF": 3523
        },
        "77": {
            "HP": 6489,
            "ATK": 7000,
            "DEF": 3552
        },
        "78": {
            "HP": 6538,
            "ATK": 7054,
            "DEF": 3579
        },
        "79": {
            "HP": 6588,
            "ATK": 7108,
            "DEF": 3605
        },
        "80": {
            "HP": 6640,
            "ATK": 7165,
            "DEF": 3634
        },
        "81": {
            "HP": 6689,
            "ATK": 7219,
            "DEF": 3661
        },
        "82": {
            "HP": 6741,
            "ATK": 7276,
            "DEF": 3689
        },
        "83": {
            "HP": 6790,
            "ATK": 7330,
            "DEF": 3716
        },
        "84": {
            "HP": 6840,
            "ATK": 7384,
            "DEF": 3743
        },
        "85": {
            "HP": 6892,
            "ATK": 7441,
            "DEF": 3771
        },
        "86": {
            "HP": 6941,
            "ATK": 7495,
            "DEF": 3798
        },
        "87": {
            "HP": 6993,
            "ATK": 7552,
            "DEF": 3826
        },
        "88": {
            "HP": 7043,
            "ATK": 7606,
            "DEF": 3853
        },
        "89": {
            "HP": 7092,
            "ATK": 7660,
            "DEF": 3880
        },
        "90": {
            "HP": 7144,
            "ATK": 7717,
            "DEF": 3909
        },
        "91": {
            "HP": 7193,
            "ATK": 7771,
            "DEF": 3935
        },
        "92": {
            "HP": 7246,
            "ATK": 7828,
            "DEF": 3964
        },
        "93": {
            "HP": 7295,
            "ATK": 7882,
            "DEF": 3991
        },
        "94": {
            "HP": 7347,
            "ATK": 7939,
            "DEF": 4019
        },
        "95": {
            "HP": 7396,
            "ATK": 7993,
            "DEF": 4046
        },
        "96": {
            "HP": 7446,
            "ATK": 8047,
            "DEF": 4073
        },
        "97": {
            "HP": 7498,
            "ATK": 8104,
            "DEF": 4101
        },
        "98": {
            "HP": 7547,
            "ATK": 8158,
            "DEF": 4128
        },
        "99": {
            "HP": 7599,
            "ATK": 8215,
            "DEF": 4156
        },
        "100": {
            "HP": 7649,
            "ATK": 8269,
            "DEF": 4183
        },
        "101": {
            "HP": 7698,
            "ATK": 8323,
            "DEF": 4210
        },
        "102": {
            "HP": 7750,
            "ATK": 8380,
            "DEF": 4238
        },
        "103": {
            "HP": 7799,
            "ATK": 8434,
            "DEF": 4265
        },
        "104": {
            "HP": 7852,
            "ATK": 8491,
            "DEF": 4294
        },
        "105": {
            "HP": 7901,
            "ATK": 8545,
            "DEF": 4321
        },
        "106": {
            "HP": 7950,
            "ATK": 8599,
            "DEF": 4347
        },
        "107": {
            "HP": 8002,
            "ATK": 8656,
            "DEF": 4376
        },
        "108": {
            "HP": 8052,
            "ATK": 8710,
            "DEF": 4403
        },
        "109": {
            "HP": 8104,
            "ATK": 8767,
            "DEF": 4431
        },
        "110": {
            "HP": 8153,
            "ATK": 8821,
            "DEF": 4458
        },
        "111": {
            "HP": 8202,
            "ATK": 8875,
            "DEF": 4485
        },
        "112": {
            "HP": 8255,
            "ATK": 8932,
            "DEF": 4513
        },
        "113": {
            "HP": 8304,
            "ATK": 8986,
            "DEF": 4540
        },
        "114": {
            "HP": 8356,
            "ATK": 9044,
            "DEF": 4568
        },
        "115": {
            "HP": 8405,
            "ATK": 9097,
            "DEF": 4595
        },
        "116": {
            "HP": 8455,
            "ATK": 9151,
            "DEF": 4622
        },
        "117": {
            "HP": 8507,
            "ATK": 9209,
            "DEF": 4650
        },
        "118": {
            "HP": 8556,
            "ATK": 9262,
            "DEF": 4677
        },
        "119": {
            "HP": 8608,
            "ATK": 9320,
            "DEF": 4706
        },
        "120": {
            "HP": 8658,
            "ATK": 9374,
            "DEF": 4733
        }
    },
    "Leader Skill": {
        "Name": "Frontline Courage",
        "9676": {
            "Buff": {
                "Type": "Percentage",
                "+ or -": "+"
            },
            "Target": {
                "Category": [
                    "Saviors"
                ],
                "Excluded Category": [],
                "Allies or enemies": "Allies",
                "Class": []
            },
            "HP": 120,
            "ATK": 120,
            "DEF": 120
        },
        "9677": {
            "Buff": {
                "Type": "Raw stats",
                "+ or -": "+"
            },
            "Target": {
                "Category": [
                    "Saviors"
                ],
                "Excluded Category": [],
                "Allies or enemies": "Allies"
            },
            "Ki": 3
        }
    },
    "Hidden Potential": {
        "0": {
            "HP": 2000,
            "ATK": 2000,
            "DEF": 2000,
            "Additional": 0,
            "Crit": 5,
            "Evasion": 0,
            "Type ATK": 6,
            "Type DEF": 5,
            "Super Attack boost": 6,
            "Recovery boost": 6
        },
        "1": {
            "HP": 300,
            "ATK": 300,
            "DEF": 300,
            "Additional": 0,
            "Crit": 0,
            "Evasion": 0,
            "Type ATK": 1,
            "Type DEF": 1,
            "Super Attack boost": 1,
            "Recovery boost": 1
        },
        "2": {
            "HP": 310,
            "ATK": 700,
            "DEF": 310,
            "Additional": 0,
            "Crit": 0,
            "Evasion": 0,
            "Type ATK": 2,
            "Type DEF": 1,
            "Super Attack boost": 1,
            "Recovery boost": 1
        },
        "3": {
            "HP": 690,
            "ATK": 300,
            "DEF": 690,
            "Additional": 0,
            "Crit": 0,
            "Evasion": 0,
            "Type ATK": 0,
            "Type DEF": 2,
            "Super Attack boost": 1,
            "Recovery boost": 1
        },
        "4": {
            "HP": 1300,
            "ATK": 2100,
            "DEF": 1700,
            "Additional": 0,
            "Crit": 0,
            "Evasion": 0,
            "Type ATK": 1,
            "Type DEF": 1,
            "Super Attack boost": 1,
            "Recovery boost": 1
        }
    },
    "Super Attack": {
        "2968": {
            "superID": "2968",
            "special_name_no": "0",
            "superName": "Kamehameha",
            "superDescription": "Raises DEF for 1 turn and \ncauses supreme damage to enemy",
            "superMinKi": "12",
            "superPriority": "0.0",
            "superStyle": "Normal",
            "superMinLVL": "0",
            "superCausality": "",
            "superAimTarget": "0",
            "superBuffs": {
                "2968": {
                    "Type": "NormalEfficacySpecial",
                    "Chance": "100",
                    "Duration": "1",
                    "Buff": {
                        "Type": "Percentage",
                        "+ or -": "+"
                    },
                    "Target": "Self",
                    "DEF": "30"
                }
            },
            "superIsInactive": "0",
            "SpecialBonus": {
                "ID": "0"
            },
            "Multiplier": 430
        }
    },
    "Active Skill": null,
    "Standby Skill": {},
    "Finish Skill": {},
    "Transforms from": [],
    "Transformations": [],
    "Dokkan awakenings": [],
    "Dokkan Reverse awakenings": [
        "1021860",
        "1021861"
    ],
    "Ki Multiplier": {
        "0": 70.0,
        "1": 75.83333333333333,
        "2": 81.66666666666667,
        "3": 87.5,
        "4": 93.33333333333333,
        "5": 99.16666666666667,
        "6": 105.0,
        "7": 110.83333333333334,
        "8": 116.66666666666666,
        "9": 122.5,
        "10": 128.33333333333334,
        "11": 134.16666666666666,
        "12": 140.0
    },
    "Ki Circle Segments": {
        "1": "weaker",
        "2": "weaker",
        "3": "weaker",
        "4": "weaker",
        "5": "weaker",
        "6": "equal",
        "7": "equal",
        "8": "equal",
        "9": "equal",
        "10": "equal",
        "11": "equal",
        "12": "super"
    },
    "Can EZA": false,
    "Can SEZA": false
}